LICENSE
MANIFEST.in
README.rst
setup.py
bootstrap_vz.egg-info/PKG-INFO
bootstrap_vz.egg-info/SOURCES.txt
bootstrap_vz.egg-info/dependency_links.txt
bootstrap_vz.egg-info/entry_points.txt
bootstrap_vz.egg-info/requires.txt
bootstrap_vz.egg-info/top_level.txt
bootstrapvz/__init__.py
bootstrapvz/base/__init__.py
bootstrapvz/base/bootstrapinfo.py
bootstrapvz/base/log.py
bootstrapvz/base/main.py
bootstrapvz/base/manifest-schema.yml
bootstrapvz/base/manifest.py
bootstrapvz/base/metaschema.json
bootstrapvz/base/phase.py
bootstrapvz/base/task.py
bootstrapvz/base/tasklist.py
bootstrapvz/base/fs/__init__.py
bootstrapvz/base/fs/exceptions.py
bootstrapvz/base/fs/volume.py
bootstrapvz/base/fs/partitionmaps/__init__.py
bootstrapvz/base/fs/partitionmaps/abstract.py
bootstrapvz/base/fs/partitionmaps/gpt.py
bootstrapvz/base/fs/partitionmaps/msdos.py
bootstrapvz/base/fs/partitionmaps/none.py
bootstrapvz/base/fs/partitions/__init__.py
bootstrapvz/base/fs/partitions/abstract.py
bootstrapvz/base/fs/partitions/base.py
bootstrapvz/base/fs/partitions/gpt.py
bootstrapvz/base/fs/partitions/gpt_swap.py
bootstrapvz/base/fs/partitions/mount.py
bootstrapvz/base/fs/partitions/msdos.py
bootstrapvz/base/fs/partitions/msdos_swap.py
bootstrapvz/base/fs/partitions/single.py
bootstrapvz/base/fs/partitions/unformatted.py
bootstrapvz/base/pkg/__init__.py
bootstrapvz/base/pkg/exceptions.py
bootstrapvz/base/pkg/packagelist.py
bootstrapvz/base/pkg/preferenceslist.py
bootstrapvz/base/pkg/sourceslist.py
bootstrapvz/common/__init__.py
bootstrapvz/common/bytes.py
bootstrapvz/common/exceptions.py
bootstrapvz/common/fsm_proxy.py
bootstrapvz/common/minify_json.py
bootstrapvz/common/phases.py
bootstrapvz/common/releases.py
bootstrapvz/common/sectors.py
bootstrapvz/common/task_groups.py
bootstrapvz/common/tools.py
bootstrapvz/common/fs/__init__.py
bootstrapvz/common/fs/folder.py
bootstrapvz/common/fs/loopbackvolume.py
bootstrapvz/common/fs/qemuvolume.py
bootstrapvz/common/fs/virtualdiskimage.py
bootstrapvz/common/fs/virtualharddisk.py
bootstrapvz/common/fs/virtualmachinedisk.py
bootstrapvz/common/tasks/__init__.py
bootstrapvz/common/tasks/apt.py
bootstrapvz/common/tasks/boot.py
bootstrapvz/common/tasks/bootstrap.py
