Metadata-Version: 1.0
Name: bootstrap-vz
Version: 0.9.11
Summary: Bootstrap Debian images for virtualized environments
Home-page: http://www.github.com/andsens/bootstrap-vz
Author: Anders Ingemann
Author-email: anders@ingemann.de
License: Apache License, Version 2.0
Platform: UNKNOWN
